machc/logger/__init__.py
machc/logger/default_log_publisher.py
machc/logger/logger.py
machc_logger-0.0.2.dist-info/METADATA
machc_logger-0.0.2.dist-info/WHEEL
machc_logger-0.0.2.dist-info/top_level.txt
machc_logger-0.0.2.dist-info/RECORD
