Metadata-Version: 2.4
Name: machc.logger
Version: 0.0.2
Summary: A logging wrapper designed for debugging and monitoring applications within the Machanism ecosystem.
Author-email: Viktor Tovstyi <viktor.tovstyi@gmail.com>
Requires-Python: ==3.12.3
